dnavi/DNAvi.py
dnavi/__init__.py
dnavi/__main__.py
dnavi/config/nucleosomal_fractions.txt
dnavi/src/__init__.py
dnavi/src/analyze_electrophero.py
dnavi/src/analyze_gel.py
dnavi/src/constants.py
dnavi/src/data_checks.py
dnavi/src/plotting.py
dnavi/src/utils.py
dnavi/tests/electropherogram.csv
dnavi/tests/example_cells.csv
dnavi/tests/gel.png
dnavi/tests/ladder.csv
dnavi/tests/metadata.csv
dnavi/tests/metadata_cells.csv
dnavi/tests/metadata_gel.csv
dnavi/tests/metadata_multi.csv
dnavi/tests/multifolder/gel1.png
dnavi/tests/multifolder/gel2.png
dnavi/tests/multifolder/gel3.png
dnavi-0.0.0.0.3.dist-info/METADATA
dnavi-0.0.0.0.3.dist-info/WHEEL
dnavi-0.0.0.0.3.dist-info/entry_points.txt
dnavi-0.0.0.0.3.dist-info/licenses/LICENSE
dnavi-0.0.0.0.3.dist-info/RECORD
