Metadata-Version: 2.4
Name: dnavi
Version: 0.0.0.0.3
Summary: DNA fragmentation analysis from electropherograms
Project-URL: Homepage, https://github.com/anjahess/DNAvi
Project-URL: Documentation, https://dnavi.readthedocs.io/en/latest/
Project-URL: Issues, https://github.com/anjahess/DNAvi/issues
Author-email: Anja Hess <anja.hess@mail.de>
License-Expression: GPL-3.0-or-later
License-File: LICENSE
Keywords: DNA,base pair,cancer,cell-free DNA,cfDNA,chromatin,ctDNA,diagnostics,electrophoresis,epigenetics,fragmentomics,gel,nucleosome
Classifier: Intended Audience :: Science/Research
Classifier: Operating System :: POSIX :: Linux
Classifier: Programming Language :: Python :: 3
Requires-Python: >=3.12
Requires-Dist: imageio
Requires-Dist: matplotlib
Requires-Dist: numpy
Requires-Dist: pandas
Requires-Dist: scikit-image
Requires-Dist: scikit-posthocs
Requires-Dist: scipy
Requires-Dist: seaborn
Requires-Dist: werkzeug
